MANIFEST.in
README.rst
requirements.txt
setup.cfg
setup.py
djmicrosip_cotizacion_puertas/__init__.py
djmicrosip_cotizacion_puertas/__init__.pyc
djmicrosip_cotizacion_puertas/config.pyc
djmicrosip_cotizacion_puertas/forms.pyc
djmicrosip_cotizacion_puertas/models.pyc
djmicrosip_cotizacion_puertas/send_mail.pyc
djmicrosip_cotizacion_puertas/storage.pyc
djmicrosip_cotizacion_puertas/urls.pyc
djmicrosip_cotizacion_puertas/views.pyc
djmicrosip_cotizacion_puertas.egg-info/PKG-INFO
djmicrosip_cotizacion_puertas.egg-info/SOURCES.txt
djmicrosip_cotizacion_puertas.egg-info/dependency_links.txt
djmicrosip_cotizacion_puertas.egg-info/requires.txt
djmicrosip_cotizacion_puertas.egg-info/top_level.txt
djmicrosip_cotizacion_puertas/static/djmicrosip_cotizacion_puertas/js/cotizacion.js
djmicrosip_cotizacion_puertas/templates/djmicrosip_cotizacion_puertas/base.html
djmicrosip_cotizacion_puertas/templates/djmicrosip_cotizacion_puertas/cotizacion.html
djmicrosip_cotizacion_puertas/templates/djmicrosip_cotizacion_puertas/imprimir.html
djmicrosip_cotizacion_puertas/templates/djmicrosip_cotizacion_puertas/index.html
djmicrosip_cotizacion_puertas/templates/djmicrosip_cotizacion_puertas/preferencias.html